src/__init__.py
src/GoogleNews/__init__.py
src/GoogleNews/setup.py
src/GoogleNews/GoogleNews/ProxyPool.py
src/GoogleNews/GoogleNews/ProxyRequests.py
src/GoogleNews/GoogleNews/UserAgent.py
src/GoogleNews/GoogleNews/__init__.py
src/GoogleNews/test/__init__.py
src/GoogleNews/test/test_search.py
src/GoogleNews/test/test_sort.py
src/Retrospective/ChromeDriver.py
src/Retrospective/GoogleNewsDriver.py
src/Retrospective/ProxyPool.py
src/Retrospective/ProxyPoolTestCase.py
src/Retrospective/ProxyRequests.py
src/Retrospective/ProxyRequestsTestCase.py
src/Retrospective/Retrospective.py
src/Retrospective/UserAgent.py
src/Retrospective/UserAgentTestCase.py
src/Retrospective/__init__.py
src/Retrospective/test.py
springbok_retrospective-0.0.1.dist-info/METADATA
springbok_retrospective-0.0.1.dist-info/WHEEL
springbok_retrospective-0.0.1.dist-info/entry_points.txt
springbok_retrospective-0.0.1.dist-info/top_level.txt
springbok_retrospective-0.0.1.dist-info/RECORD
