Metadata-Version: 2.1
Name: springbok-retrospective
Version: 0.0.1
Summary: A project to look at the greatest hits of news about a specific topic and add that to a blog
Home-page: https://github.com/ralatsdc/springbok-retrospective
Author: Springbok
Author-email: raymond.leclair@springbok.io
Classifier: Programming Language :: Python :: 3
Classifier: License :: OSI Approved :: GNU General Public License v3 or later (GPLv3+)
Classifier: Operating System :: OS Independent
Requires-Python: >=3.7
Requires-Dist: selenium
Requires-Dist: requests
Requires-Dist: wget
Requires-Dist: python-dateutil
Requires-Dist: bs4
Requires-Dist: boto
Requires-Dist: boto3
